hippo/__init__.py
hippo/_version.py
hippo/camelyon_utils.py
hippo/search.py
hippo/models/__init__.py
hippo/models/abmil.py
hippo_nn-0.1.0.dist-info/METADATA
hippo_nn-0.1.0.dist-info/WHEEL
hippo_nn-0.1.0.dist-info/licenses/LICENSE
hippo_nn-0.1.0.dist-info/RECORD
