Metadata-Version: 2.3
Name: hippo-nn
Version: 0.1.0
Summary: HIPPO explainability toolkit for computational pathology.
Project-URL: Repository, https://github.com/kaczmarj/HIPPO
Project-URL: Bug Tracker, https://github.com/kaczmarj/HIPPO/issues
Author-email: Jakub Kaczmarzyk <jakub.kaczmarzyk@gmail.com>
Maintainer-email: Jakub Kaczmarzyk <jakub.kaczmarzyk@gmail.com>
License: BSD 3-Clause License
License-File: LICENSE
Keywords: abmil,computational pathology,counterfactuals,deep learning,explainability,multiple instance learning,pathology
Classifier: Development Status :: 4 - Beta
Classifier: Programming Language :: Python
Requires-Python: >=3.8
Requires-Dist: numpy>=1.20
Requires-Dist: torch>=1.9
Requires-Dist: tqdm
Provides-Extra: dev
Requires-Dist: pytest; extra == 'dev'
Requires-Dist: ruff; extra == 'dev'
